Metadata-Version: 2.1
Name: pyadigraph
Version: 0.0.1
Summary: Pyadigraph turns your networkx into Adigraph latex package.
Home-page: https://github.com/LucaCappelletti94/pyadigraph
Author: Luca Cappelletti
Author-email: cappelletti.luca94@gmail.com
License: MIT
Platform: UNKNOWN
Classifier: Development Status :: 4 - Beta
Classifier: License :: OSI Approved :: MIT License
Classifier: Programming Language :: Python :: 3
Provides-Extra: test
